botface/__init__.py
jobhub/__init__.py
jobhub-0.0.1.dist-info/METADATA
jobhub-0.0.1.dist-info/WHEEL
jobhub-0.0.1.dist-info/top_level.txt
jobhub-0.0.1.dist-info/RECORD
