Metadata-Version: 2.1
Name: jobhub
Version: 0.0.1
Summary: Async message queue system
Home-page: https://github.com/inspora/jobhub
Author: Daniel Birnstiel
Author-email: daniel@inspora.com
License: UNKNOWN
Platform: UNKNOWN
Classifier: Programming Language :: Python
Classifier: Programming Language :: Python :: 3
Classifier: Programming Language :: Python :: 3.7
Classifier: Programming Language :: Python :: Implementation :: CPython
Classifier: Programming Language :: Python :: Implementation :: PyPy
Requires-Python: >=3.6.0
